llm_cost_calculator/__init__.py
llm_cost_calculator/cost_tracker.py
llm_cost_calculator/pricing.py
llm_cost_calculator/token_counter.py
llm_cost_calculator-3.0.0.dist-info/licenses/LICENSE
llm_cost_calculator-3.0.0.dist-info/METADATA
llm_cost_calculator-3.0.0.dist-info/WHEEL
llm_cost_calculator-3.0.0.dist-info/top_level.txt
llm_cost_calculator-3.0.0.dist-info/RECORD
